CHANGES.rst
CONTRIBUTORS.rst
MANIFEST.in
README.rst
setup.cfg
setup.py
docs/LICENSE.GPL
docs/LICENSE.rst
src/spirit/__init__.py
src/spirit.plone.sitemanagement.egg-info/PKG-INFO
src/spirit.plone.sitemanagement.egg-info/SOURCES.txt
src/spirit.plone.sitemanagement.egg-info/dependency_links.txt
src/spirit.plone.sitemanagement.egg-info/entry_points.txt
src/spirit.plone.sitemanagement.egg-info/namespace_packages.txt
src/spirit.plone.sitemanagement.egg-info/not-zip-safe
src/spirit.plone.sitemanagement.egg-info/requires.txt
src/spirit.plone.sitemanagement.egg-info/top_level.txt
src/spirit/plone/__init__.py
src/spirit/plone/sitemanagement/__init__.py
src/spirit/plone/sitemanagement/admin.py
src/spirit/plone/sitemanagement/config.py
src/spirit/plone/sitemanagement/configure.zcml
src/spirit/plone/sitemanagement/assets/bootstrap.min.css
src/spirit/plone/sitemanagement/assets/sitemanagement.css
src/spirit/plone/sitemanagement/templates/plone-sitemanagement.pt