Metadata-Version: 1.1
Name: spirit.plone.sitemanagement
Version: 0.3
Summary: Control your Plone sites from one management screen.
Home-page: https://github.com/it-spirit/spirit.plone.sitemanagement
Author: it-spirit
Author-email: thomas.massmann@it-spir.it
License: GPL version 2
Download-URL: http://pypi.python.org/pypi/spirit.plone.sitemanagement
Keywords: plone zope management
Platform: UNKNOWN
Classifier: Development Status :: 4 - Beta
Classifier: Environment :: Web Environment
Classifier: Framework :: Plone
Classifier: Framework :: Plone :: 4.1
Classifier: Framework :: Plone :: 4.2
Classifier: Framework :: Plone :: 4.3
Classifier: Framework :: Plone :: 5.0
Classifier: Framework :: Plone :: 5.1
Classifier: Intended Audience :: Developers
Classifier: License :: OSI Approved :: GNU General Public License v2 (GPLv2)
Classifier: Programming Language :: Python
Classifier: Programming Language :: Python :: 2.6
Classifier: Programming Language :: Python :: 2.7
